mapcache.py
mapcache-0.1.3.data/scripts/mapcache.py
mapcache-0.1.3.dist-info/LICENSE
mapcache-0.1.3.dist-info/METADATA
mapcache-0.1.3.dist-info/WHEEL
mapcache-0.1.3.dist-info/entry_points.txt
mapcache-0.1.3.dist-info/top_level.txt
mapcache-0.1.3.dist-info/RECORD
