Metadata-Version: 2.1
Name: mapcache
Version: 0.1.3
Summary: Simple caching server for map tiles
Home-page: https://github.com/luphord/mapcache
Author: luphord
Author-email: luphord@protonmail.com
License: MIT license
Keywords: mapcache
Platform: UNKNOWN
Classifier: Development Status :: 3 - Alpha
Classifier: Intended Audience :: Developers
Classifier: License :: OSI Approved :: MIT License
Classifier: Natural Language :: English
Classifier: Programming Language :: Python :: 3
Classifier: Programming Language :: Python :: 3.5
Classifier: Programming Language :: Python :: 3.6
Classifier: Programming Language :: Python :: 3.7
